meta/__init__.py
meta/metamodel.py
meta/metamodel_cmd.py
meta/mw.py
meta/profiler.py
meta/sidif2linkml.py
meta/smw_type.py
meta/uml.py
meta/version.py
pymetamodel-0.6.6.dist-info/METADATA
pymetamodel-0.6.6.dist-info/WHEEL
pymetamodel-0.6.6.dist-info/entry_points.txt
pymetamodel-0.6.6.dist-info/licenses/LICENSE
pymetamodel-0.6.6.dist-info/RECORD
