Metadata-Version: 2.4
Name: pyMetaModel
Version: 0.6.6
Dynamic: Summary
Project-URL: Home, https://github.com/WolfgangFahl/pyMetaModel
Project-URL: Documentation, https://wiki.bitplan.com/index.php/PyMetaModel
Project-URL: Source, https://github.com/WolfgangFahl/pyMetaModel
Author-email: Wolfgang Fahl <wf@bitplan.com>
Maintainer-email: Wolfgang Fahl <wf@bitplan.com>
License:                                  Apache License
License-File: LICENSE
Classifier: Development Status :: 4 - Beta
Classifier: Environment :: Web Environment
Classifier: Intended Audience :: Developers
Classifier: Intended Audience :: Science/Research
Classifier: License :: OSI Approved :: Apache Software License
Classifier: Operating System :: OS Independent
Classifier: Programming Language :: Python :: 3 :: Only
Classifier: Programming Language :: Python :: 3.10
Classifier: Programming Language :: Python :: 3.11
Classifier: Programming Language :: Python :: 3.12
Classifier: Programming Language :: Python :: 3.13
Classifier: Topic :: Software Development
Requires-Python: >=3.10
Requires-Dist: py-sidif>=0.2.0
Requires-Dist: pybasemkit>=0.0.4
Requires-Dist: urllib3
Provides-Extra: linkml
Requires-Dist: linkml-runtime>=1.8.3; extra == 'linkml'
Requires-Dist: linkml>=1.8.5; extra == 'linkml'
Provides-Extra: smw
Requires-Dist: mwparserfromhell>=0.6.6; extra == 'smw'
Requires-Dist: py-3rdparty-mediawiki>=0.14.0; extra == 'smw'
Provides-Extra: test
Requires-Dist: green; extra == 'test'
